README.md
setup.py
bin/ponster
ponster/__init__.py
ponster/annotations_pb2.py
ponster/annotations_pb2_grpc.py
ponster/device_info.py
ponster/http_pb2.py
ponster/http_pb2_grpc.py
ponster/ind.py
ponster/openolt_pb2.py
ponster/openolt_pb2_grpc.py
ponster.egg-info/PKG-INFO
ponster.egg-info/SOURCES.txt
ponster.egg-info/dependency_links.txt
ponster.egg-info/requires.txt
ponster.egg-info/top_level.txt